genericclient/__init__.py
genericclient/exceptions.py
genericclient/pagination.py
genericclient/routes.py
genericclient/utils.py
tests/__init__.py
tests/test_auth.py
tests/test_client.py
tests/test_endpoint.py
tests/test_endpoint_trailing_slash.py
tests/test_paginate.py
tests/test_resource.py
tests/test_resource_trailing_slash.py
tests/test_routes.py
genericclient-1.4.2.dist-info/LICENSE
genericclient-1.4.2.dist-info/METADATA
genericclient-1.4.2.dist-info/WHEEL
genericclient-1.4.2.dist-info/top_level.txt
genericclient-1.4.2.dist-info/RECORD
